mbrtools.py
MBRTools-1.1.dist-info/LICENSE
MBRTools-1.1.dist-info/METADATA
MBRTools-1.1.dist-info/WHEEL
MBRTools-1.1.dist-info/top_level.txt
MBRTools-1.1.dist-info/RECORD
