Metadata-Version: 2.1
Name: MBRTools
Version: 1.1
Summary: MBRTools
Author: bilibili2022
Requires-Python: >=3
License-File: LICENSE
